Metadata-Version: 1.1
Name: ocw
Version: 1.3.0
Summary: Apache Open Climate Workbench
Home-page: http://climate.apache.org/
Author: Apache Open Climate Workbench
Author-email: dev@climate.apache.org
License: Apache License, Version 2.0
Download-URL: http://pypi.python.org/pypi/ocw/
Keywords: climate analysis,workbench,rebinning,metrics,computation,visualization
Platform: UNKNOWN
Classifier: Environment :: Console
Classifier: Intended Audience :: Developers
Classifier: Intended Audience :: Information Technology
Classifier: Intended Audience :: Science/Research
Classifier: Topic :: Scientific/Engineering
Classifier: Development Status :: 5 - Production/Stable
Classifier: License :: OSI Approved :: Apache Software License
Classifier: Operating System :: OS Independent
Classifier: Programming Language :: Python
Classifier: Topic :: Internet :: WWW/HTTP
Classifier: Topic :: Software Development :: Libraries :: Python Modules
